faker_crypto/__init__.py
faker_crypto-1.0.1.dist-info/METADATA
faker_crypto-1.0.1.dist-info/WHEEL
faker_crypto-1.0.1.dist-info/RECORD
