Metadata-Version: 2.4
Name: faker-crypto
Version: 1.0.1
Summary: faker-crypto is a Faker provider for cryto addreses.
Project-URL: Repository, https://github.com/karambir/faker-crypto
Project-URL: Homepage, https://github.com/karambir/faker-crypto/
Project-URL: Issues, https://github.com/karambir/faker-crypto/issues
Author-email: Karambir Singh Nain <hello@karambir.in>
License: MIT
Keywords: cryptocurrency,faker,generator,mock,test
Classifier: Development Status :: 5 - Production/Stable
Classifier: Intended Audience :: Developers
Classifier: License :: OSI Approved :: MIT License
Classifier: Programming Language :: Python :: 3
Classifier: Programming Language :: Python :: 3.9
Classifier: Programming Language :: Python :: 3.10
Classifier: Programming Language :: Python :: 3.11
Classifier: Programming Language :: Python :: 3.12
Classifier: Programming Language :: Python :: 3.13
Classifier: Programming Language :: Python :: 3.14
Classifier: Topic :: Software Development :: Libraries :: Python Modules
Classifier: Topic :: Software Development :: Testing
Classifier: Topic :: Utilities
Requires-Python: >=3.9
Requires-Dist: faker>=14.2
